{
    "mobileBottomRow": 24,
    "widgetName": "Divider2",
    "thickness": 2,
    "displayName": "Divider",
    "iconSVG": "/static/media/icon.3b7d47d7bd70da418a827287042cbb7f.svg",
    "searchTags": ["line"],
    "topRow": 11,
    "bottomRow": 42,
    "parentRowSpace": 10,
    "type": "DIVIDER_WIDGET",
    "capType": "nc",
    "hideCard": false,
    "mobileRightColumn": 42,
    "animateLoading": true,
    "parentColumnSpace": 17.66583251953125,
    "dynamicTriggerPathList": [],
    "leftColumn": 14,
    "dynamicBindingPathList": [],
    "key": "8b5h3ziot0",
    "dividerColor": "#858282",
    "orientation": "vertical",
    "strokeStyle": "solid",
    "isDeprecated": false,
    "rightColumn": 17,
    "widgetId": "jz758ylyxv",
    "capSide": 0,
    "minWidth": 450,
    "isVisible": true,
    "version": 1,
    "parentId": "2nv6cbjeee",
    "tags": ["Layout"],
    "renderMode": "CANVAS",
    "isLoading": false,
    "mobileTopRow": 20,
    "responsiveBehavior": "fill",
    "originalTopRow": 11,
    "mobileLeftColumn": 22,
    "originalBottomRow": 42
}